crcset/__init__.py
crcset/crcset_wasi.py
crcset/crcset_wasm.py
crcset/wasi/__init__.py
crcset/wasi/_crcset_wasi.wasm
crcset/wasi/wasi.py
crcset/wasm/__init__.py
crcset/wasm/_crcset_wasm.wasm
crcset/wasm/wasm.py
crcset-0.0.4.dist-info/LICENSE
crcset-0.0.4.dist-info/METADATA
crcset-0.0.4.dist-info/WHEEL
crcset-0.0.4.dist-info/top_level.txt
crcset-0.0.4.dist-info/RECORD
