Metadata-Version: 2.1
Name: crcset
Version: 0.0.4
Home-page: https://github.com/AminRezaei0x443/crcset
Author: Amin Rezaei
Author-email: AminRezaei0x443@gmail.com
License: MIT
License-File: LICENSE
Requires-Dist: wasmer (~=1.1.0)
Requires-Dist: wasmer-compiler-cranelift (~=1.1.0)
Requires-Dist: pywasm (~=1.0.7)
